pyLINQ/__init__.py
pyLINQ/main.py
pythonLINQ/__init__.py
pyLINQ-0.5.0.dist-info/LICENSE.txt
pyLINQ-0.5.0.dist-info/METADATA
pyLINQ-0.5.0.dist-info/WHEEL
pyLINQ-0.5.0.dist-info/top_level.txt
pyLINQ-0.5.0.dist-info/RECORD
