Metadata-Version: 2.1
Name: pyLINQ
Version: 0.5.0
Summary: Makes filtering and sorting lists easier and more readable.
Home-page: https://github.com/jmfernandes/pyLINQ
Author: Josh Fernandes
Author-email: joshfernandes@mac.com
License: MIT
Keywords: LINQ,list,list comprehension,lambda,utility,C#,where,set,filter,sort
Platform: UNKNOWN
Requires-Python: >=3.4
